mait_manager/main.py
mait_manager-0.1.6.1.dist-info/entry_points.txt
mait_manager-0.1.6.1.dist-info/WHEEL
mait_manager-0.1.6.1.dist-info/METADATA
mait_manager-0.1.6.1.dist-info/RECORD
