Metadata-Version: 2.1
Name: mait-manager
Version: 0.1.6.1
Summary: 
Author: Zayne Marsh
Author-email: you@example.com
Requires-Python: >=3.8,<4.0
Classifier: Programming Language :: Python :: 3
Classifier: Programming Language :: Python :: 3.8
Classifier: Programming Language :: Python :: 3.9
Classifier: Programming Language :: Python :: 3.10
Requires-Dist: typer (>=0.6.1,<0.7.0)
